<ColorMaps>
<ColorMap name="bilbaoS" space="HSV">
  <Point x="0.000000" o="1" r="0.974435" g="0.974358" b="0.974039"/>
  <Point x="0.010101" o="1" r="0.300376" g="0.001865" b="0.005395"/>
  <Point x="0.020202" o="1" r="0.663627" g="0.520134" b="0.394568"/>
  <Point x="0.030303" o="1" r="0.754652" g="0.729719" b="0.635662"/>
  <Point x="0.040404" o="1" r="0.571467" g="0.286727" b="0.273138"/>
  <Point x="0.050505" o="1" r="0.632388" g="0.413162" b="0.347757"/>
  <Point x="0.060606" o="1" r="0.703297" g="0.636487" b="0.474567"/>
  <Point x="0.070707" o="1" r="0.445612" g="0.148030" b="0.146005"/>
  <Point x="0.080808" o="1" r="0.829163" g="0.824018" b="0.805059"/>
  <Point x="0.090909" o="1" r="0.610727" g="0.354275" b="0.318430"/>
  <Point x="0.101010" o="1" r="0.730024" g="0.690405" b="0.553729"/>
  <Point x="0.111111" o="1" r="0.681188" g="0.577655" b="0.424282"/>
  <Point x="0.121212" o="1" r="0.899502" g="0.898571" b="0.895136"/>
  <Point x="0.131313" o="1" r="0.375996" g="0.080518" b="0.085505"/>
  <Point x="0.141414" o="1" r="0.648744" g="0.468501" b="0.372005"/>
  <Point x="0.151515" o="1" r="0.515257" g="0.218851" b="0.214337"/>
  <Point x="0.161616" o="1" r="0.784061" g="0.770509" b="0.719827"/>
  <Point x="0.171717" o="1" r="0.640761" g="0.440978" b="0.360072"/>
  <Point x="0.181818" o="1" r="0.671940" g="0.548283" b="0.407838"/>
  <Point x="0.191919" o="1" r="0.337762" g="0.039997" b="0.052327"/>
  <Point x="0.202020" o="1" r="0.594049" g="0.321667" b="0.298383"/>
  <Point x="0.212121" o="1" r="0.622861" g="0.384515" b="0.334327"/>
  <Point x="0.222222" o="1" r="0.862214" g="0.859804" b="0.850916"/>
  <Point x="0.232323" o="1" r="0.767923" g="0.748868" b="0.676996"/>
  <Point x="0.242424" o="1" r="0.481101" g="0.183191" b="0.180154"/>
  <Point x="0.252525" o="1" r="0.716866" g="0.665801" b="0.512632"/>
  <Point x="0.262626" o="1" r="0.742411" g="0.710966" b="0.594852"/>
  <Point x="0.272727" o="1" r="0.547040" g="0.255099" b="0.247090"/>
  <Point x="0.282828" o="1" r="0.933995" g="0.933657" b="0.932390"/>
  <Point x="0.292929" o="1" r="0.805259" g="0.796638" b="0.764685"/>
  <Point x="0.303030" o="1" r="0.655654" g="0.492529" b="0.382411"/>
  <Point x="0.313131" o="1" r="0.690669" g="0.604815" b="0.443906"/>
  <Point x="0.323232" o="1" r="0.408998" g="0.112652" b="0.112911"/>
  <Point x="0.333333" o="1" r="0.583522" g="0.304447" b="0.286411"/>
  <Point x="0.343434" o="1" r="0.761061" g="0.739121" b="0.656203"/>
  <Point x="0.353535" o="1" r="0.603070" g="0.338286" b="0.309040"/>
  <Point x="0.363636" o="1" r="0.318914" g="0.019130" b="0.029528"/>
  <Point x="0.373737" o="1" r="0.463498" g="0.165567" b="0.163022"/>
  <Point x="0.383838" o="1" r="0.880465" g="0.878932" b="0.873268"/>
  <Point x="0.393939" o="1" r="0.710058" g="0.651650" b="0.492920"/>
  <Point x="0.404040" o="1" r="0.696777" g="0.620722" b="0.458106"/>
  <Point x="0.414141" o="1" r="0.627843" g="0.398978" b="0.341245"/>
  <Point x="0.424242" o="1" r="0.644772" g="0.454769" b="0.366071"/>
  <Point x="0.434343" o="1" r="0.531549" g="0.236932" b="0.231003"/>
  <Point x="0.444444" o="1" r="0.736284" g="0.701060" b="0.574352"/>
  <Point x="0.454545" o="1" r="0.793901" g="0.782910" b="0.742011"/>
  <Point x="0.464646" o="1" r="0.845013" g="0.841412" b="0.828132"/>
  <Point x="0.474747" o="1" r="0.498400" g="0.200920" b="0.197330"/>
  <Point x="0.484848" o="1" r="0.748486" g="0.720419" b="0.615252"/>
  <Point x="0.494949" o="1" r="0.676401" g="0.562768" b="0.415472"/>
  <Point x="0.505051" o="1" r="0.659616" g="0.506298" b="0.388428"/>
  <Point x="0.515152" o="1" r="0.775495" g="0.759241" b="0.698164"/>
  <Point x="0.525253" o="1" r="0.617237" g="0.369651" b="0.326778"/>
  <Point x="0.535354" o="1" r="0.667713" g="0.534100" b="0.400984"/>
  <Point x="0.545455" o="1" r="0.954127" g="0.953954" b="0.953293"/>
  <Point x="0.555556" o="1" r="0.356840" g="0.061064" b="0.070322"/>
  <Point x="0.565657" o="1" r="0.723542" g="0.678717" b="0.533065"/>
  <Point x="0.575758" o="1" r="0.427462" g="0.130453" b="0.129227"/>
  <Point x="0.585859" o="1" r="0.636661" g="0.427139" b="0.353989"/>
  <Point x="0.595960" o="1" r="0.686422" g="0.593027" b="0.434736"/>
  <Point x="0.606061" o="1" r="0.914142" g="0.913527" b="0.911239"/>
  <Point x="0.616162" o="1" r="0.818287" g="0.811776" b="0.787700"/>
  <Point x="0.626263" o="1" r="0.394960" g="0.099059" b="0.100920"/>
  <Point x="0.636364" o="1" r="0.651708" g="0.478798" b="0.376473"/>
  <Point x="0.646465" o="1" r="0.557977" g="0.268718" b="0.258637"/>
  <Point x="0.656566" o="1" r="0.607060" g="0.346357" b="0.313876"/>
  <Point x="0.666667" o="1" r="0.564888" g="0.277757" b="0.266032"/>
  <Point x="0.676768" o="1" r="0.683745" g="0.585289" b="0.429275"/>
  <Point x="0.686869" o="1" r="0.625416" g="0.391797" b="0.337839"/>
  <Point x="0.696970" o="1" r="0.853457" g="0.850496" b="0.839577"/>
  <Point x="0.707071" o="1" r="0.366423" g="0.070994" b="0.078058"/>
  <Point x="0.717172" o="1" r="0.779633" g="0.764750" b="0.708936"/>
  <Point x="0.727273" o="1" r="0.745444" g="0.715734" b="0.605060"/>
  <Point x="0.737374" o="1" r="0.523492" g="0.227872" b="0.222732"/>
  <Point x="0.747475" o="1" r="0.669806" g="0.541155" b="0.404328"/>
  <Point x="0.757576" o="1" r="0.577680" g="0.295640" b="0.279940"/>
  <Point x="0.767677" o="1" r="0.706662" g="0.644164" b="0.483533"/>
  <Point x="0.777778" o="1" r="0.751551" g="0.725077" b="0.625451"/>
  <Point x="0.787879" o="1" r="0.944035" g="0.943790" b="0.942869"/>
  <Point x="0.797980" o="1" r="0.620149" g="0.377148" b="0.330636"/>
  <Point x="0.808081" o="1" r="0.678746" g="0.570149" b="0.419707"/>
  <Point x="0.818182" o="1" r="0.674134" g="0.555468" b="0.411534"/>
  <Point x="0.828283" o="1" r="0.634552" g="0.420163" b="0.350908"/>
  <Point x="0.838384" o="1" r="0.889901" g="0.888705" b="0.884263"/>
  <Point x="0.848485" o="1" r="0.726810" g="0.684706" b="0.543393"/>
  <Point x="0.858586" o="1" r="0.489788" g="0.192048" b="0.188761"/>
  <Point x="0.868687" o="1" r="0.598740" g="0.330068" b="0.303864"/>
  <Point x="0.878788" o="1" r="0.811565" g="0.804034" b="0.776162"/>
  <Point x="0.888889" o="1" r="0.799381" g="0.789604" b="0.753290"/>
  <Point x="0.898990" o="1" r="0.836903" g="0.832574" b="0.816622"/>
  <Point x="0.909091" o="1" r="0.964260" g="0.964141" b="0.963676"/>
  <Point x="0.919192" o="1" r="0.661615" g="0.513211" b="0.391481"/>
  <Point x="0.929293" o="1" r="0.588974" g="0.313131" b="0.292572"/>
  <Point x="0.939394" o="1" r="0.506884" g="0.209869" b="0.205872"/>
  <Point x="0.949495" o="1" r="0.646765" g="0.461638" b="0.369046"/>
  <Point x="0.959596" o="1" r="0.771609" g="0.753964" b="0.687524"/>
  <Point x="0.969697" o="1" r="0.614102" g="0.362040" b="0.322736"/>
  <Point x="0.979798" o="1" r="0.764422" g="0.743932" b="0.666550"/>
  <Point x="0.989899" o="1" r="0.757813" g="0.734390" b="0.645904"/>
  <Point x="1.000000" o="1" r="0.788802" g="0.776556" b="0.730851"/>
</ColorMap>
</ColorMaps>